{"stats":{"minecraft:mined":{"minecraft:fire":1,"minecraft:tnt":1},"minecraft:picked_up":{"minecraft:birch_log":5},"minecraft:used":{"minecraft:flint_and_steel":2,"minecraft:tnt":4,"minecraft:cooked_porkchop":1,"minecraft:porkchop":3},"minecraft:custom":{"minecraft:jump":29,"minecraft:time_since_rest":1095,"minecraft:sprint_one_cm":1566,"minecraft:play_time":1095,"minecraft:damage_taken":20,"minecraft:time_since_death":1095,"minecraft:walk_one_cm":2431,"minecraft:total_world_time":1953,"minecraft:fall_one_cm":974,"minecraft:fly_one_cm":4739}},"DataVersion":3120}